{
  "project": "Add React Router",
  "branchName": "ralph/add-react-router",
  "description": "Install react-router-dom dependency for routing functionality",
  "userStories": [
    {
      "id": "US-001",
      "notes": "",
      "title": "Install react-router-dom package",
      "passes": true,
      "priority": 1,
      "description": "As a developer, I need to add react-router-dom to the project dependencies.",
      "acceptanceCriteria": [
        "Execute 'npm install react-router-dom' in project root",
        "react-router-dom appears in package.json dependencies",
        "react-router-dom directory exists in node_modules",
        "Typecheck passes"
      ]
    }
  ]
}